Metadata-Version: 2.4
Name: pycompilation
Version: 0.4.13
Summary: pycompilation is a package for meta programming. It aims to support
Home-page: https://github.com/bjodah/pycompilation
Author: Bjoern I. Dahlgren
Author-email: bjodah@gmail.com
License: BSD
Classifier: Development Status :: 3 - Alpha
Classifier: Intended Audience :: Developers
Classifier: License :: OSI Approved :: BSD License
Classifier: Operating System :: POSIX
Classifier: Programming Language :: Python
Classifier: Programming Language :: C
Classifier: Programming Language :: C++
Classifier: Programming Language :: Cython
Classifier: Programming Language :: Fortran
Classifier: Topic :: Software Development :: Code Generators
Classifier: Topic :: Software Development :: Compilers
Classifier: Topic :: Software Development :: Libraries :: Python Modules
License-File: LICENSE
License-File: AUTHORS
Provides-Extra: all
Requires-Dist: cython; extra == "all"
Requires-Dist: appdirs; extra == "all"
Requires-Dist: argh; extra == "all"
Requires-Dist: joblib; extra == "all"
Requires-Dist: pytest; extra == "all"
Requires-Dist: numpy; extra == "all"
Requires-Dist: Sphinx; extra == "all"
Requires-Dist: sphinx_rtd_theme; extra == "all"
Requires-Dist: numpydoc; extra == "all"
Requires-Dist: pytest-cov; extra == "all"
Requires-Dist: pytest-flakes; extra == "all"
Requires-Dist: pytest-pep8; extra == "all"
Dynamic: author
Dynamic: author-email
Dynamic: classifier
Dynamic: description
Dynamic: home-page
Dynamic: license
Dynamic: license-file
Dynamic: provides-extra
Dynamic: summary
